{
  "question" : "그림 (가)와 (나)는 고생대 이후 서로 다른 두 시기의 대륙 분포를 나타낸 것이다.",
  "category" : "[0, 0, 0]"
},
{
  "question" : "그림은 태평양판에 위치한 열점들에 의해 형성된 섬과 해산의 일부를 나타낸 것이다.",
  "category" : "[0, 0, 0]"
},
{
  "question" : "그림 (가)와 (나)는 서로 다른 퇴적 구조를 나타낸 것이다.",
  "category" : "[0, 0, 0]"
},
{
  "question" : "그림 (가)와 (나)는 각각 태평양과 대서양에서 측정한 해령으로 부터의 거리에 따른 해양 지각의 연령과 수심을 나타낸 것이다.",
  "category" : "[0, 0, 0]"
},
{
  "question" : "그림은 어느 지역의 지질 단면도를, 표는 화성암 P와 Q에 포함된 방사성 원소 X와 이 원소가 붕괴되어 생성된 자원소의 함량을 나타낸 것이다.",
  "category" : "[0, 0, 0]"
},
{
  "question" : "다음은 지질 시대에 대한 원격 수업 장면이다. ",
  "category" : "[0, 0, 0]"
},
{
  "question" : "그림은 세 지역 A, B, C의 지질 단면과 지층에서 산출되는 화석을 나타낸 것이다. ",
  "category" : "[0, 0, 0]"
},
{
  "question" : "그림 (가)와 (나)는 어느 시기 우리나라 주변의 표층 수온과 표층 염분을 나타낸 것이다.",
  "category" : "[0, 0, 0]"
},
{
  "question" : "다음은 위성 영상을 해석하는 탐구 활동이다. ",
  "category" : "[0, 0, 0]"
},
{
  "question" : "그림 (가)와 (나)는 겨울철 어느 날 6시간 간격으로 작성된 지상 일기도를 순서 없이 나타낸 것이다.",
  "category" : "[0, 0, 0]"
},
{
  "question" : "표는 어느 태풍의 중심 기압과 이동 속도를, 그림은 이 태풍이 우리나라를 통과할 때 어느 관측소에서 측정한 기온과 풍향 및 풍속을 나타낸 것이다.",
  "category" : "[0, 0, 0]"
},
{
  "question" : "표는 심층 순환을 이루는 수괴에 대한 설명을 나타낸 것이다. (가), (나), (다)는 각각 남극 저층수, 북대서양 심층수, 남극 중층수 중 하나이다.",
  "category" : "[0, 0, 0]"
},
{
  "question" : "그림은 주계열성 A와 B가 각각 거성 A′와 B′로 진화하는 경로의 일부를 H-R도에 나타낸 것이다.",
  "category" : "[0, 0, 0]"
},
{
  "question" : "그림은 과거 지구 자전축의 경사각과 지구 공전 궤도 이심률 변화를 나타낸 것이다. ",
  "category" : "[0, 0, 0]"
},
{
  "question" : "그림은 태평양 적도 해역의 해수면으로부터 수심 300 m까지의 평균 수온 편차(관측값 - 평년값)를 나타낸 것이다. A와 B는 각각 엘니뇨와 라니냐 시기 중 하나이다.",
  "category" : "[0, 0, 0]"
},
{
  "question" : "그림은 지구 대기권 밖에서 단위 시간 동안 관측한 주계열성 A, B, C의 복사 에너지 세기를 파장에 따라 나타낸 것이다.",
  "category" : "[0, 0, 0]"
},
{
  "question" : "그림은 별 A ～ D의 상대적 크기를, 표는 별의 물리량을 나타낸 것이다. 별 A ～ D는 각각 ㉠ ～ ",
  "category" : "[0, 0, 0]"
},
{
  "question" : "표는 우리은하에서 관측한 외부 은하 A와 B의 흡수선 파장과 거리를 나타낸 것이다. A에서 관측한 B의 후퇴 속도는 17300 km/s이고, 세 은하는 허블 법칙을 만족한다.",
  "category" : "[0, 0, 0]"
},
{
  "question" : "그림은 외계 행성이 중심별 주위를 공전하며 식현상을 일으키는 모습과 중심별의 밝기 변화를 나타낸 것이다. 이 외계 행성에 의해 중심별의 도플러 효과가 관측된다.",
  "category" : "[0, 0, 0]"
},
{
  "question" : "그림은 우주 모형 A, B와 외부 은하에서 발견된 Ⅰ형 초신성의 관측 자료를 나타낸 것이다. 과 는 각각 현재 우주의 물질 밀도와 암흑 에너지 밀도를 임계 밀도로 나눈 값이다.",
  "category" : "[0, 0, 0]"
},
