{
  "question" : "다음은 판 구조론이 정립되는 과정에서 등장한 세 이론 (가), (나), (다)와 학생 A, B, C의 대화를 나타낸 것이다.",
  "category" : "[0, 0, 0]"
},
{
  "question" : "그림은 1991년부터 2020년까지 제주 지역의 연간 열대야 일수와 폭염 일수를 나타낸 것이다.",
  "category" : "[0, 0, 0]"
},
{
  "question" : "그림 (가)는 대서양의 해수 순환을, (나)는 대서양 해수의 연직 순환을 나타낸 모식도이다. A, B, C는 각각 남극 저층수, 북대서양 심층수, 표층수 중 하나이다.",
  "category" : "[0, 0, 0]"
},
{
  "question" : "그림은 2019년 10월부터 2020년 7월까지 태평양 적도 해역에서 20 ℃ 등수온선의 깊이 편차(관측값 - 평년값)를 나타낸 것이다. ㉠과 ㉡은 각각 엘니뇨 시기와 라니냐 시기 중 하나이다.",
  "category" : "[0, 0, 0]"
},
{
  "question" : "그림은 어느 판 경계 부근에서 진원의 평균 깊이를 점선으로 나타낸 것이다. A와 B 지점 중 한 곳은 대륙판에, 다른 한 곳은 해양판에 위치한다.",
  "category" : "[0, 0, 0]"
},
{
  "question" : "그림 (가)는 어느 날 21시의 일기도이고, (나)는 같은 시각의 위성 영상이다.",
  "category" : "[0, 0, 0]"
},
{
  "question" : "그림은 행성이 주계열성인 중심별로부터 받는 복사 에너지와 중심별의 표면 온도를 나타낸 것이다. 행성 A, B, C 중 B와 C만 생명 가능 지대에 위치하며 A와 B의 반지름은 같다.",
  "category" : "[0, 0, 0]"
},
{
  "question" : "그림 (가)는 어느 해 겨울에 우리나라 주변 바다에서 표층 해수를 채취한 A와 B 지점의 위치를, (나)는 수온 - 염분도에 A와 B의 수온과 염분을 순서 없이 ㉠, ㉡으로 나타낸 것이다.",
  "category" : "[0, 0, 0]"
},
{
  "question" : "그림은 중심부의 핵융합 반응이 끝난 별 (가)와 (나)의 내부 구조를 나타낸 것이다.",
  "category" : "[0, 0, 0]"
},
{
  "question" : "그림은 현생 누대의 일부를 기 단위로 구분하여 생물의 생존 기간과 번성 정도를 나타낸 것이다. ㉠과 ㉡은 각각 양치식물과 겉씨식물 중 하나이다.",
  "category" : "[0, 0, 0]"
},
{
  "question" : "그림은 깊이에 따른 지하의 온도 분포와 맨틀의 용융 곡선 X, Y를 나타낸 것이다. X, Y는 각각 물이 포함된 맨틀의 용융 곡선과 물이 포함되지 않은 맨틀의 용융 곡선 중 하나이고, ㉠, ㉡은 마그마의 생성 과정이다.",
  "category" : "[0, 0, 0]"
},
{
  "question" : "그림 (가)는 H-R도를, (나)는 별 A와 B 중 하나의 중심부에서 일어나는 핵융합 반응을 나타낸 것이다.",
  "category" : "[0, 0, 0]"
},
{
  "question" : "그림은 주계열성 (가)와 (나)가 방출하는 복사 에너지의 상대적인 세기를 파장에 따라 나타낸 것이다. (가)와 (나)의 분광형은 각각 A0형과 G2형 중 하나이다.",
  "category" : "[0, 0, 0]"
},
{
  "question" : "표는 어느 날 03시, 12시, 21시의 태풍 중심 위치와 중심 기압이고, 그림은 이날 12시의 우리나라 부근의 일기도이다.",
  "category" : "[0, 0, 0]"
},
{
  "question" : "그림 (가), (나), (다)는 주상 절리, 습곡, 사층리를 순서 없이 나타낸 것이다.",
  "category" : "[0, 0, 0]"
},
{
  "question" : "그림 (가), (나), (다)는 타원 은하, 나선 은하, 불규칙 은하를 순서 없이 나타낸 것이다.",
  "category" : "[0, 0, 0]"
},
{
  "question" : "그림 (가)는 어느 지역의 지질 단면을, (나)는 방사성 원소 X와 Y의 붕괴 곡선을 나타낸 것이다. 화성암 P와 Q 중 하나에는 X가, 다른 하나에는 Y가 포함되어 있다. X와 Y의 처음 양은 같았으며, P와 Q에 포함되어 있는 방사성 원소의 양은 각각 처음 양의 25%와 50%이다.",
  "category" : "[0, 0, 0]"
},
{
  "question" : "다음은 스펙트럼을 이용하여 외부 은하의 후퇴 속도를 구하는 탐구이다.",
  "category" : "[0, 0, 0]"
},
{
  "question" : "그림은 현재 지구의 공전 궤도와 자전축 경사를 나타낸 것이다. a는 원일점 거리, b는 근일점 거리, 는 지구의 공전 궤도면과 자전축이 이루는 각이다.",
  "category" : "[0, 0, 0]"
},
{
  "question" : "표는 현재 우주 구성 요소 A, B, C의 비율이고, 그림은 시간에 따른 우주의 상대적 크기 변화를 나타낸 것이다. A, B, C는 각각 보통 물질, 암흑 물질, 암흑 에너지 중 하나이다.",
  "category" : "[0, 0, 0]"
},
